README.md
setup.py
transferboost/__init__.py
transferboost/dataset.py
transferboost.egg-info/PKG-INFO
transferboost.egg-info/SOURCES.txt
transferboost.egg-info/dependency_links.txt
transferboost.egg-info/not-zip-safe
transferboost.egg-info/requires.txt
transferboost.egg-info/top_level.txt
transferboost/models/__init__.py
transferboost/models/lgb.py
transferboost/models/xgb.py
transferboost/utils/__init__.py
transferboost/utils/analysis_utils.py
transferboost/utils/boost.py
transferboost/utils/exceptions.py
transferboost/utils/loss_functions.py
transferboost/utils/utils.py