Metadata-Version: 2.1
Name: transferboost
Version: 0.1.1
Summary: Transfer Learning with Gradient Boosting Models
Home-page: https://github.com/sbjelogr/TransferBoost
Author: Sandro Bjelogrlic
Author-email: sandro.bjelogrlic@gmail.com
License: MIT license
Platform: UNKNOWN
Classifier: Programming Language :: Python :: 3
Classifier: License :: OSI Approved :: MIT License
Classifier: Operating System :: OS Independent
Requires-Python: >=3.6
